<?xml version="1.0" encoding="UTF-8"?>
<PeakList>
  <PeakList1D>
    <PeakList1DHeader creator="emanuele" date="2024-07-23T22:21:53.535+01:00" expNo="10" name="batch5-35" owner="" procNo="1" source="C:\Users\emanuele\Desktop\PlacementEssay\PlacementEssay\backup\ChemspeedPlatformAllVersions\V12\Workflows\Data\Reactions\batch5\NmrData">
      <PeakPickDetails>F1=12.499880ppm, F2=-3.099771ppm, MI=0.00cm, MAXI=10000.00cm, PC=5.000
      </PeakPickDetails>
    </PeakList1DHeader>
    <Peak1D F1="1.992106" intensity="1.317818e+02" type="0"/>
    <Peak1D F1="1.948583" intensity="1.752169e+02" type="0"/>
    <Peak1D F1="1.917395" intensity="2.000000e+02" type="0"/>
    <Peak1D F1="0.068076" intensity="1.670700e+01" type="0"/>
  </PeakList1D>
</PeakList>
