<?xml version="1.0" encoding="UTF-8"?>
<PeakList>
  <PeakList1D>
    <PeakList1DHeader creator="emanuele" date="2024-07-23T21:42:40.610+01:00" expNo="10" name="batch0-18" owner="" procNo="1" source="C:\Users\emanuele\Desktop\PlacementEssay\PlacementEssay\backup\ChemspeedPlatformAllVersions\V12\Workflows\Data\Reactions\batch0\NmrData">
      <PeakPickDetails>F1=12.463430ppm, F2=-3.136220ppm, MI=0.00cm, MAXI=10000.00cm, PC=5.000
      </PeakPickDetails>
    </PeakList1DHeader>
    <Peak1D F1="9.896933" intensity="1.228629e+00" type="0"/>
    <Peak1D F1="7.248074" intensity="3.872791e+00" type="0"/>
    <Peak1D F1="3.979394" intensity="8.137494e+00" type="0"/>
    <Peak1D F1="3.701620" intensity="4.825858e+00" type="0"/>
    <Peak1D F1="2.170714" intensity="1.032563e+02" type="0"/>
    <Peak1D F1="1.999582" intensity="1.826929e+02" type="0"/>
    <Peak1D F1="1.935137" intensity="2.000000e+02" type="0"/>
    <Peak1D F1="0.077742" intensity="1.053608e+01" type="0"/>
  </PeakList1D>
</PeakList>
