[{"file":"batch1-01\\10\\pdata\\1\\","type":"Dataset","path":"","name":"batch1-01","procno":1,"expno":10,"title":"batch1-01\n1batch1: [6-Methylpyridine-2-carboxaldehyde, Zinc tetrafluoroborate, 4,4'-Methylenedianiline]\nMULTISUPPDC_f","date":"2024-02-29T10:12:30Z","dataType":null,"specType":"","sf":80.130376615,"pulProg":"noesycpdcgpps1d","nuclei":"1H","solvent":"CH3CN","parMode":0,"pparMode":0,"timestamp":"2024-07-28T17:15:17.821048Z"},{"file":"batch1-01\\1001001\\pdata\\1\\","type":"Dataset","path":"","name":"batch1-01","procno":1,"expno":1001001,"title":"batch1-01\n1batch1: [6-Methylpyridine-2-carboxaldehyde, Zinc tetrafluoroborate, 4,4'-Methylenedianiline]\nMULTISUPPDC_f\nPeaks for suppression at (in Hz):\n236.97; 169.25; 100.73; ","date":"2024-02-29T10:04:43Z","dataType":null,"specType":"PROTON","sf":80.130494803,"pulProg":"zg30","nuclei":"1H","solvent":"CH3CN","parMode":0,"pparMode":0,"timestamp":"2024-07-28T17:15:09.108971Z"},{"file":"batch1-01\\1001002\\pdata\\1\\","type":"Dataset","path":"","name":"batch1-01","procno":1,"expno":1001002,"title":"batch1-01\n1batch1: [6-Methylpyridine-2-carboxaldehyde, Zinc tetrafluoroborate, 4,4'-Methylenedianiline]\nMULTISUPPDC_f","date":"2024-02-29T10:04:55Z","dataType":null,"specType":"DEPT45","sf":20.150719396,"pulProg":"deptsp45","nuclei":"13C","solvent":"CH3CN","parMode":0,"pparMode":0,"timestamp":"2024-07-28T17:15:20.571616Z"},{"file":"batch1-02\\10\\pdata\\1\\","type":"Dataset","path":"","name":"batch1-02","procno":1,"expno":10,"title":"batch1-02\n48: [1-Methyl-2-imidazolecarboxaldehyde, Naphthalene-1,8-diamine, Iron(II) tetrafluoroborate hexahydrate]\nMULTISUPPDC_f","date":"2024-02-29T10:23:39Z","dataType":null,"specType":"","sf":80.130376615,"pulProg":"noesycpdcgpps1d","nuclei":"1H","solvent":"CH3CN","parMode":0,"pparMode":0,"timestamp":"2024-07-28T17:15:16.267997Z"},{"file":"batch1-02\\1001001\\pdata\\1\\","type":"Dataset","path":"","name":"batch1-02","procno":1,"expno":1001001,"title":"batch1-02\n48: [1-Methyl-2-imidazolecarboxaldehyde, Naphthalene-1,8-diamine, Iron(II) tetrafluoroborate hexahydrate]\nMULTISUPPDC_f\nPeaks for suppression at (in Hz):\n235.30; 167.58; 99.06; ","date":"2024-02-29T10:15:52Z","dataType":null,"specType":"PROTON","sf":80.130494803,"pulProg":"zg30","nuclei":"1H","solvent":"CH3CN","parMode":0,"pparMode":0,"timestamp":"2024-07-28T17:15:22.047164Z"},{"file":"batch1-02\\1001002\\pdata\\1\\","type":"Dataset","path":"","name":"batch1-02","procno":1,"expno":1001002,"title":"batch1-02\n48: [1-Methyl-2-imidazolecarboxaldehyde, Naphthalene-1,8-diamine, Iron(II) tetrafluoroborate hexahydrate]\nMULTISUPPDC_f","date":"2024-02-29T10:16:04Z","dataType":null,"specType":"DEPT45","sf":20.150719396,"pulProg":"deptsp45","nuclei":"13C","solvent":"CH3CN","parMode":0,"pparMode":0,"timestamp":"2024-07-28T17:15:19.235477Z"},{"file":"batch1-03\\10\\pdata\\1\\","type":"Dataset","path":"","name":"batch1-03","procno":1,"expno":10,"title":"batch1-03\n49: [1-Methyl-2-imidazolecarboxaldehyde, 4,4'-(9H-Fluorene-9,9-diyl)dianiline, Iron(II) tetrafluoroborate hexahydrate]\nMULTISUPPDC_f","date":"2024-02-29T10:34:46Z","dataType":null,"specType":"","sf":80.130376615,"pulProg":"noesycpdcgpps1d","nuclei":"1H","solvent":"CH3CN","parMode":0,"pparMode":0,"timestamp":"2024-07-28T17:15:19.688595Z"},{"file":"batch1-03\\1001001\\pdata\\1\\","type":"Dataset","path":"","name":"batch1-03","procno":1,"expno":1001001,"title":"batch1-03\n49: [1-Methyl-2-imidazolecarboxaldehyde, 4,4'-(9H-Fluorene-9,9-diyl)dianiline, Iron(II) tetrafluoroborate hexahydrate]\nMULTISUPPDC_f\nPeaks for suppression at (in Hz):\n236.94; 169.22; 100.70; ","date":"2024-02-29T10:27:00Z","dataType":null,"specType":"PROTON","sf":80.130494803,"pulProg":"zg30","nuclei":"1H","solvent":"CH3CN","parMode":0,"pparMode":0,"timestamp":"2024-07-28T17:15:20.085219Z"},{"file":"batch1-03\\1001002\\pdata\\1\\","type":"Dataset","path":"","name":"batch1-03","procno":1,"expno":1001002,"title":"batch1-03\n49: [1-Methyl-2-imidazolecarboxaldehyde, 4,4'-(9H-Fluorene-9,9-diyl)dianiline, Iron(II) tetrafluoroborate hexahydrate]\nMULTISUPPDC_f","date":"2024-02-29T10:27:11Z","dataType":null,"specType":"DEPT45","sf":20.150719396,"pulProg":"deptsp45","nuclei":"13C","solvent":"CH3CN","parMode":0,"pparMode":0,"timestamp":"2024-07-28T17:15:17.829497Z"},{"file":"batch1-04\\10\\pdata\\1\\","type":"Dataset","path":"","name":"batch1-04","procno":1,"expno":10,"title":"batch1-04\n50: [2,2'-(Ethane-1,2-diyl)dianiline, 6-Methoxypyridine-2-carbaldehyde, Iron(II) tetrafluoroborate hexahydrate]\nMULTISUPPDC_f","date":"2024-02-29T10:45:54Z","dataType":null,"specType":"","sf":80.130376615,"pulProg":"noesycpdcgpps1d","nuclei":"1H","solvent":"CH3CN","parMode":0,"pparMode":0,"timestamp":"2024-07-28T17:15:09.118459Z"},{"file":"batch1-04\\1001001\\pdata\\1\\","type":"Dataset","path":"","name":"batch1-04","procno":1,"expno":1001001,"title":"batch1-04\n50: [2,2'-(Ethane-1,2-diyl)dianiline, 6-Methoxypyridine-2-carbaldehyde, Iron(II) tetrafluoroborate hexahydrate]\nMULTISUPPDC_f\nPeaks for suppression at (in Hz):\n235.97; 168.23; 99.73; ","date":"2024-02-29T10:38:07Z","dataType":null,"specType":"PROTON","sf":80.130494803,"pulProg":"zg30","nuclei":"1H","solvent":"CH3CN","parMode":0,"pparMode":0,"timestamp":"2024-07-28T17:15:20.584958Z"},{"file":"batch1-04\\1001002\\pdata\\1\\","type":"Dataset","path":"","name":"batch1-04","procno":1,"expno":1001002,"title":"batch1-04\n50: [2,2'-(Ethane-1,2-diyl)dianiline, 6-Methoxypyridine-2-carbaldehyde, Iron(II) tetrafluoroborate hexahydrate]\nMULTISUPPDC_f\nPeaks for suppression at (in Hz):\n20.17; ","date":"2024-02-29T10:38:18Z","dataType":null,"specType":"DEPT45","sf":20.150719396,"pulProg":"deptsp45","nuclei":"13C","solvent":"CH3CN","parMode":0,"pparMode":0,"timestamp":"2024-07-28T17:15:16.270988Z"},{"file":"batch1-05\\10\\pdata\\1\\","type":"Dataset","path":"","name":"batch1-05","procno":1,"expno":10,"title":"batch1-05\n51: [2,2'-(Ethane-1,2-diyl)dianiline, 5-Methylpicolinaldehyde, Zinc tetrafluoroborate]\nMULTISUPPDC_f","date":"2024-02-29T10:57:01Z","dataType":null,"specType":"","sf":80.130376615,"pulProg":"noesycpdcgpps1d","nuclei":"1H","solvent":"CH3CN","parMode":0,"pparMode":0,"timestamp":"2024-07-28T17:15:22.052163Z"},{"file":"batch1-05\\1001001\\pdata\\1\\","type":"Dataset","path":"","name":"batch1-05","procno":1,"expno":1001001,"title":"batch1-05\n51: [2,2'-(Ethane-1,2-diyl)dianiline, 5-Methylpicolinaldehyde, Zinc tetrafluoroborate]\nMULTISUPPDC_f\nPeaks for suppression at (in Hz):\n236.67; 168.94; 100.43; ","date":"2024-02-29T10:49:14Z","dataType":null,"specType":"PROTON","sf":80.130494803,"pulProg":"zg30","nuclei":"1H","solvent":"CH3CN","parMode":0,"pparMode":0,"timestamp":"2024-07-28T17:15:19.244313Z"},{"file":"batch1-05\\1001002\\pdata\\1\\","type":"Dataset","path":"","name":"batch1-05","procno":1,"expno":1001002,"title":"batch1-05\n51: [2,2'-(Ethane-1,2-diyl)dianiline, 5-Methylpicolinaldehyde, Zinc tetrafluoroborate]\nMULTISUPPDC_f","date":"2024-02-29T10:49:25Z","dataType":null,"specType":"DEPT45","sf":20.150719396,"pulProg":"deptsp45","nuclei":"13C","solvent":"CH3CN","parMode":0,"pparMode":0,"timestamp":"2024-07-28T17:15:19.702288Z"},{"file":"batch1-06\\10\\pdata\\1\\","type":"Dataset","path":"","name":"batch1-06","procno":1,"expno":10,"title":"batch1-06\n52: [2,2'-(Ethane-1,2-diyl)dianiline, 5-Methylpicolinaldehyde, Iron(II) tetrafluoroborate hexahydrate]\nMULTISUPPDC_f","date":"2024-02-29T11:08:10Z","dataType":null,"specType":"","sf":80.130376615,"pulProg":"noesycpdcgpps1d","nuclei":"1H","solvent":"CH3CN","parMode":0,"pparMode":0,"timestamp":"2024-07-28T17:15:20.089087Z"},{"file":"batch1-06\\1001001\\pdata\\1\\","type":"Dataset","path":"","name":"batch1-06","procno":1,"expno":1001001,"title":"batch1-06\n52: [2,2'-(Ethane-1,2-diyl)dianiline, 5-Methylpicolinaldehyde, Iron(II) tetrafluoroborate hexahydrate]\nMULTISUPPDC_f\nPeaks for suppression at (in Hz):\n236.85; 169.11; 100.61; ","date":"2024-02-29T11:00:23Z","dataType":null,"specType":"PROTON","sf":80.130494803,"pulProg":"zg30","nuclei":"1H","solvent":"CH3CN","parMode":0,"pparMode":0,"timestamp":"2024-07-28T17:15:17.836067Z"},{"file":"batch1-06\\1001002\\pdata\\1\\","type":"Dataset","path":"","name":"batch1-06","procno":1,"expno":1001002,"title":"batch1-06\n52: [2,2'-(Ethane-1,2-diyl)dianiline, 5-Methylpicolinaldehyde, Iron(II) tetrafluoroborate hexahydrate]\nMULTISUPPDC_f","date":"2024-02-29T11:00:35Z","dataType":null,"specType":"DEPT45","sf":20.150719396,"pulProg":"deptsp45","nuclei":"13C","solvent":"CH3CN","parMode":0,"pparMode":0,"timestamp":"2024-07-28T17:15:09.131310Z"},{"file":"batch1-07\\10\\pdata\\1\\","type":"Dataset","path":"","name":"batch1-07","procno":1,"expno":10,"title":"batch1-07\n53: [1-Methyl-2-imidazolecarboxaldehyde, 1,3-Benzenedimethanamine, Zinc tetrafluoroborate]\nMULTISUPPDC_f","date":"2024-02-29T11:19:18Z","dataType":null,"specType":"","sf":80.130376615,"pulProg":"noesycpdcgpps1d","nuclei":"1H","solvent":"CH3CN","parMode":0,"pparMode":0,"timestamp":"2024-07-28T17:15:20.597174Z"},{"file":"batch1-07\\1001001\\pdata\\1\\","type":"Dataset","path":"","name":"batch1-07","procno":1,"expno":1001001,"title":"batch1-07\n53: [1-Methyl-2-imidazolecarboxaldehyde, 1,3-Benzenedimethanamine, Zinc tetrafluoroborate]\nMULTISUPPDC_f\nPeaks for suppression at (in Hz):\n237.28; 185.54; 169.55; 101.04; ","date":"2024-02-29T11:11:32Z","dataType":null,"specType":"PROTON","sf":80.130494803,"pulProg":"zg30","nuclei":"1H","solvent":"CH3CN","parMode":0,"pparMode":0,"timestamp":"2024-07-28T17:15:16.282918Z"},{"file":"batch1-07\\1001002\\pdata\\1\\","type":"Dataset","path":"","name":"batch1-07","procno":1,"expno":1001002,"title":"batch1-07\n53: [1-Methyl-2-imidazolecarboxaldehyde, 1,3-Benzenedimethanamine, Zinc tetrafluoroborate]\nMULTISUPPDC_f","date":"2024-02-29T11:11:43Z","dataType":null,"specType":"DEPT45","sf":20.150719396,"pulProg":"deptsp45","nuclei":"13C","solvent":"CH3CN","parMode":0,"pparMode":0,"timestamp":"2024-07-28T17:15:22.059503Z"},{"file":"batch1-08\\10\\pdata\\1\\","type":"Dataset","path":"","name":"batch1-08","procno":1,"expno":10,"title":"batch1-08\n54: [1-Methyl-2-imidazolecarboxaldehyde, 1,3-Benzenedimethanamine, Iron(II) tetrafluoroborate hexahydrate]\nMULTISUPPDC_f","date":"2024-02-29T11:30:27Z","dataType":null,"specType":"","sf":80.130376615,"pulProg":"noesycpdcgpps1d","nuclei":"1H","solvent":"CH3CN","parMode":0,"pparMode":0,"timestamp":"2024-07-28T17:15:19.253029Z"},{"file":"batch1-08\\1001001\\pdata\\1\\","type":"Dataset","path":"","name":"batch1-08","procno":1,"expno":1001001,"title":"batch1-08\n54: [1-Methyl-2-imidazolecarboxaldehyde, 1,3-Benzenedimethanamine, Iron(II) tetrafluoroborate hexahydrate]\nMULTISUPPDC_f\nPeaks for suppression at (in Hz):\n235.88; 168.14; 99.64; ","date":"2024-02-29T11:22:40Z","dataType":null,"specType":"PROTON","sf":80.130494803,"pulProg":"zg30","nuclei":"1H","solvent":"CH3CN","parMode":0,"pparMode":0,"timestamp":"2024-07-28T17:15:19.711073Z"},{"file":"batch1-08\\1001002\\pdata\\1\\","type":"Dataset","path":"","name":"batch1-08","procno":1,"expno":1001002,"title":"batch1-08\n54: [1-Methyl-2-imidazolecarboxaldehyde, 1,3-Benzenedimethanamine, Iron(II) tetrafluoroborate hexahydrate]\nMULTISUPPDC_f","date":"2024-02-29T11:22:52Z","dataType":null,"specType":"DEPT45","sf":20.150719396,"pulProg":"deptsp45","nuclei":"13C","solvent":"CH3CN","parMode":0,"pparMode":0,"timestamp":"2024-07-28T17:15:20.100637Z"},{"file":"batch1-09\\10\\pdata\\1\\","type":"Dataset","path":"","name":"batch1-09","procno":1,"expno":10,"title":"batch1-09\n55: [2,2'-(Ethane-1,2-diyl)dianiline, 1-Methyl-2-imidazolecarboxaldehyde, Zinc tetrafluoroborate]\nMULTISUPPDC_f","date":"2024-02-29T11:41:37Z","dataType":null,"specType":"","sf":80.130376615,"pulProg":"noesycpdcgpps1d","nuclei":"1H","solvent":"CH3CN","parMode":0,"pparMode":0,"timestamp":"2024-07-28T17:15:17.839058Z"},{"file":"batch1-09\\1001001\\pdata\\1\\","type":"Dataset","path":"","name":"batch1-09","procno":1,"expno":1001001,"title":"batch1-09\n55: [2,2'-(Ethane-1,2-diyl)dianiline, 1-Methyl-2-imidazolecarboxaldehyde, Zinc tetrafluoroborate]\nMULTISUPPDC_f\nPeaks for suppression at (in Hz):\n238.12; 187.42; 170.40; 101.87; ","date":"2024-02-29T11:33:50Z","dataType":null,"specType":"PROTON","sf":80.130494803,"pulProg":"zg30","nuclei":"1H","solvent":"CH3CN","parMode":0,"pparMode":0,"timestamp":"2024-07-28T17:15:09.137484Z"},{"file":"batch1-09\\1001002\\pdata\\1\\","type":"Dataset","path":"","name":"batch1-09","procno":1,"expno":1001002,"title":"batch1-09\n55: [2,2'-(Ethane-1,2-diyl)dianiline, 1-Methyl-2-imidazolecarboxaldehyde, Zinc tetrafluoroborate]\nMULTISUPPDC_f","date":"2024-02-29T11:34:01Z","dataType":null,"specType":"DEPT45","sf":20.150719396,"pulProg":"deptsp45","nuclei":"13C","solvent":"CH3CN","parMode":0,"pparMode":0,"timestamp":"2024-07-28T17:15:20.605099Z"},{"file":"batch1-10\\10\\pdata\\1\\","type":"Dataset","path":"","name":"batch1-10","procno":1,"expno":10,"title":"batch1-10\n56: [2,2'-(Ethane-1,2-diyl)dianiline, 1-Methyl-2-imidazolecarboxaldehyde, Iron(II) tetrafluoroborate hexahydrate]\nMULTISUPPDC_f","date":"2024-02-29T11:52:45Z","dataType":null,"specType":"","sf":80.130376615,"pulProg":"noesycpdcgpps1d","nuclei":"1H","solvent":"CH3CN","parMode":0,"pparMode":0,"timestamp":"2024-07-28T17:15:16.294548Z"},{"file":"batch1-10\\1001001\\pdata\\1\\","type":"Dataset","path":"","name":"batch1-10","procno":1,"expno":1001001,"title":"batch1-10\n56: [2,2'-(Ethane-1,2-diyl)dianiline, 1-Methyl-2-imidazolecarboxaldehyde, Iron(II) tetrafluoroborate hexahydrate]\nMULTISUPPDC_f\nPeaks for suppression at (in Hz):\n235.23; 167.50; 98.98; ","date":"2024-02-29T11:44:59Z","dataType":null,"specType":"PROTON","sf":80.130494803,"pulProg":"zg30","nuclei":"1H","solvent":"CH3CN","parMode":0,"pparMode":0,"timestamp":"2024-07-28T17:15:22.062808Z"},{"file":"batch1-10\\1001002\\pdata\\1\\","type":"Dataset","path":"","name":"batch1-10","procno":1,"expno":1001002,"title":"batch1-10\n56: [2,2'-(Ethane-1,2-diyl)dianiline, 1-Methyl-2-imidazolecarboxaldehyde, Iron(II) tetrafluoroborate hexahydrate]\nMULTISUPPDC_f","date":"2024-02-29T11:45:10Z","dataType":null,"specType":"DEPT45","sf":20.150719396,"pulProg":"deptsp45","nuclei":"13C","solvent":"CH3CN","parMode":0,"pparMode":0,"timestamp":"2024-07-28T17:15:19.266114Z"},{"file":"batch1-11\\10\\pdata\\1\\","type":"Dataset","path":"","name":"batch1-11","procno":1,"expno":10,"title":"batch1-11\n57: [Yittrium(III) trifluoromethanesulfonate, 6-Methylpyridine-2-carboxaldehyde, 4,4'-Methylenedianiline]\nMULTISUPPDC_f","date":"2024-02-29T12:03:52Z","dataType":null,"specType":"","sf":80.130376615,"pulProg":"noesycpdcgpps1d","nuclei":"1H","solvent":"CH3CN","parMode":0,"pparMode":0,"timestamp":"2024-07-28T17:15:19.725385Z"},{"file":"batch1-11\\1001001\\pdata\\1\\","type":"Dataset","path":"","name":"batch1-11","procno":1,"expno":1001001,"title":"batch1-11\n57: [Yittrium(III) trifluoromethanesulfonate, 6-Methylpyridine-2-carboxaldehyde, 4,4'-Methylenedianiline]\nMULTISUPPDC_f\nPeaks for suppression at (in Hz):\n236.60; 168.89; 100.36; ","date":"2024-02-29T11:56:06Z","dataType":null,"specType":"PROTON","sf":80.130494803,"pulProg":"zg30","nuclei":"1H","solvent":"CH3CN","parMode":0,"pparMode":0,"timestamp":"2024-07-28T17:15:21.352314Z"},{"file":"batch1-11\\1001002\\pdata\\1\\","type":"Dataset","path":"","name":"batch1-11","procno":1,"expno":1001002,"title":"batch1-11\n57: [Yittrium(III) trifluoromethanesulfonate, 6-Methylpyridine-2-carboxaldehyde, 4,4'-Methylenedianiline]\nMULTISUPPDC_f","date":"2024-02-29T11:56:18Z","dataType":null,"specType":"DEPT45","sf":20.150719396,"pulProg":"deptsp45","nuclei":"13C","solvent":"CH3CN","parMode":0,"pparMode":0,"timestamp":"2024-07-28T17:15:17.852416Z"},{"file":"batch1-12\\10\\pdata\\1\\","type":"Dataset","path":"","name":"batch1-12","procno":1,"expno":10,"title":"batch1-12\n58: [Yittrium(III) trifluoromethanesulfonate, 6-Methylpyridine-2-carboxaldehyde, 2,2'-(Ethane-1,2-diylbis(oxy))diethanamine]\nMULTISUPPDC_f","date":"2024-02-29T12:15:02Z","dataType":null,"specType":"","sf":80.130376615,"pulProg":"noesycpdcgpps1d","nuclei":"1H","solvent":"CH3CN","parMode":0,"pparMode":0,"timestamp":"2024-07-28T17:15:09.184389Z"},{"file":"batch1-12\\1001001\\pdata\\1\\","type":"Dataset","path":"","name":"batch1-12","procno":1,"expno":1001001,"title":"batch1-12\n58: [Yittrium(III) trifluoromethanesulfonate, 6-Methylpyridine-2-carboxaldehyde, 2,2'-(Ethane-1,2-diylbis(oxy))diethanamine]\nMULTISUPPDC_f\nPeaks for suppression at (in Hz):\n448.33; 237.62; 169.90; 101.39; ","date":"2024-02-29T12:07:13Z","dataType":null,"specType":"PROTON","sf":80.130494803,"pulProg":"zg30","nuclei":"1H","solvent":"CH3CN","parMode":0,"pparMode":0,"timestamp":"2024-07-28T17:15:20.613874Z"},{"file":"batch1-12\\1001002\\pdata\\1\\","type":"Dataset","path":"","name":"batch1-12","procno":1,"expno":1001002,"title":"batch1-12\n58: [Yittrium(III) trifluoromethanesulfonate, 6-Methylpyridine-2-carboxaldehyde, 2,2'-(Ethane-1,2-diylbis(oxy))diethanamine]\nMULTISUPPDC_f\nPeaks for suppression at (in Hz):\n20.79; ","date":"2024-02-29T12:07:27Z","dataType":null,"specType":"DEPT45","sf":20.150719396,"pulProg":"deptsp45","nuclei":"13C","solvent":"CH3CN","parMode":0,"pparMode":0,"timestamp":"2024-07-28T17:15:16.307701Z"},{"file":"batch1-13\\10\\pdata\\1\\","type":"Dataset","path":"","name":"batch1-13","procno":1,"expno":10,"title":"batch1-13\n59: [Yittrium(III) trifluoromethanesulfonate, 6-Methylpyridine-2-carboxaldehyde, 4,4'-Oxydianiline]\nMULTISUPPDC_f","date":"2024-02-29T12:26:11Z","dataType":null,"specType":"","sf":80.130376615,"pulProg":"noesycpdcgpps1d","nuclei":"1H","solvent":"CH3CN","parMode":0,"pparMode":0,"timestamp":"2024-07-28T17:15:22.068945Z"},{"file":"batch1-13\\1001001\\pdata\\1\\","type":"Dataset","path":"","name":"batch1-13","procno":1,"expno":1001001,"title":"batch1-13\n59: [Yittrium(III) trifluoromethanesulfonate, 6-Methylpyridine-2-carboxaldehyde, 4,4'-Oxydianiline]\nMULTISUPPDC_f\nPeaks for suppression at (in Hz):\n237.28; 169.53; 101.03; ","date":"2024-02-29T12:18:25Z","dataType":null,"specType":"PROTON","sf":80.130494803,"pulProg":"zg30","nuclei":"1H","solvent":"CH3CN","parMode":0,"pparMode":0,"timestamp":"2024-07-28T17:15:19.274889Z"},{"file":"batch1-13\\1001002\\pdata\\1\\","type":"Dataset","path":"","name":"batch1-13","procno":1,"expno":1001002,"title":"batch1-13\n59: [Yittrium(III) trifluoromethanesulfonate, 6-Methylpyridine-2-carboxaldehyde, 4,4'-Oxydianiline]\nMULTISUPPDC_f","date":"2024-02-29T12:18:36Z","dataType":null,"specType":"DEPT45","sf":20.150719396,"pulProg":"deptsp45","nuclei":"13C","solvent":"CH3CN","parMode":0,"pparMode":0,"timestamp":"2024-07-28T17:15:19.749626Z"},{"file":"batch1-14\\10\\pdata\\1\\","type":"Dataset","path":"","name":"batch1-14","procno":1,"expno":10,"title":"batch1-14\n60: [Yittrium(III) trifluoromethanesulfonate, 6-Methoxypyridine-2-carbaldehyde, 4,4'-Methylenedianiline]\nMULTISUPPDC_f","date":"2024-02-29T12:37:19Z","dataType":null,"specType":"","sf":80.130376615,"pulProg":"noesycpdcgpps1d","nuclei":"1H","solvent":"CH3CN","parMode":0,"pparMode":0,"timestamp":"2024-07-28T17:15:21.364388Z"},{"file":"batch1-14\\1001001\\pdata\\1\\","type":"Dataset","path":"","name":"batch1-14","procno":1,"expno":1001001,"title":"batch1-14\n60: [Yittrium(III) trifluoromethanesulfonate, 6-Methoxypyridine-2-carbaldehyde, 4,4'-Methylenedianiline]\nMULTISUPPDC_f\nPeaks for suppression at (in Hz):\n236.56; 168.84; 100.32; ","date":"2024-02-29T12:29:32Z","dataType":null,"specType":"PROTON","sf":80.130494803,"pulProg":"zg30","nuclei":"1H","solvent":"CH3CN","parMode":0,"pparMode":0,"timestamp":"2024-07-28T17:15:17.857345Z"},{"file":"batch1-14\\1001002\\pdata\\1\\","type":"Dataset","path":"","name":"batch1-14","procno":1,"expno":1001002,"title":"batch1-14\n60: [Yittrium(III) trifluoromethanesulfonate, 6-Methoxypyridine-2-carbaldehyde, 4,4'-Methylenedianiline]\nMULTISUPPDC_f","date":"2024-02-29T12:29:43Z","dataType":null,"specType":"DEPT45","sf":20.150719396,"pulProg":"deptsp45","nuclei":"13C","solvent":"CH3CN","parMode":0,"pparMode":0,"timestamp":"2024-07-28T17:15:09.198211Z"},{"file":"batch1-17\\10\\pdata\\1\\","type":"Dataset","path":"","name":"batch1-17","procno":1,"expno":10,"title":"batch1-17\n63: [Yittrium(III) trifluoromethanesulfonate, Naphthalene-1,8-diamine, 6-Methylpyridine-2-carboxaldehyde]\nMULTISUPPDC_f","date":"2024-02-29T13:10:54Z","dataType":null,"specType":"","sf":80.130376615,"pulProg":"noesycpdcgpps1d","nuclei":"1H","solvent":"CH3CN","parMode":0,"pparMode":0,"timestamp":"2024-07-28T17:15:20.625234Z"},{"file":"batch1-17\\1001001\\pdata\\1\\","type":"Dataset","path":"","name":"batch1-17","procno":1,"expno":1001001,"title":"batch1-17\n63: [Yittrium(III) trifluoromethanesulfonate, Naphthalene-1,8-diamine, 6-Methylpyridine-2-carboxaldehyde]\nMULTISUPPDC_f\nPeaks for suppression at (in Hz):\n236.65; 168.95; 100.41; ","date":"2024-02-29T13:03:06Z","dataType":null,"specType":"PROTON","sf":80.130494803,"pulProg":"zg30","nuclei":"1H","solvent":"CH3CN","parMode":0,"pparMode":0,"timestamp":"2024-07-28T17:15:16.311308Z"},{"file":"batch1-17\\1001002\\pdata\\1\\","type":"Dataset","path":"","name":"batch1-17","procno":1,"expno":1001002,"title":"batch1-17\n63: [Yittrium(III) trifluoromethanesulfonate, Naphthalene-1,8-diamine, 6-Methylpyridine-2-carboxaldehyde]\nMULTISUPPDC_f","date":"2024-02-29T13:03:18Z","dataType":null,"specType":"DEPT45","sf":20.150719396,"pulProg":"deptsp45","nuclei":"13C","solvent":"CH3CN","parMode":0,"pparMode":0,"timestamp":"2024-07-28T17:15:22.074853Z"},{"file":"batch1-18\\10\\pdata\\1\\","type":"Dataset","path":"","name":"batch1-18","procno":1,"expno":10,"title":"batch1-18\n64: [Yittrium(III) trifluoromethanesulfonate, 4,4'-(9H-Fluorene-9,9-diyl)dianiline, 6-Methylpyridine-2-carboxaldehyde]\nMULTISUPPDC_f","date":"2024-02-29T13:46:13Z","dataType":null,"specType":"","sf":80.130376615,"pulProg":"noesycpdcgpps1d","nuclei":"1H","solvent":"CH3CN","parMode":0,"pparMode":0,"timestamp":"2024-07-28T17:15:19.283524Z"},{"file":"batch1-18\\1001001\\pdata\\1\\","type":"Dataset","path":"","name":"batch1-18","procno":1,"expno":1001001,"title":"batch1-18\n64: [Yittrium(III) trifluoromethanesulfonate, 4,4'-(9H-Fluorene-9,9-diyl)dianiline, 6-Methylpyridine-2-carboxaldehyde]\nMULTISUPPDC_f\nPeaks for suppression at (in Hz):\n236.45; 168.70; 100.21; ","date":"2024-02-29T13:38:28Z","dataType":null,"specType":"PROTON","sf":80.130494803,"pulProg":"zg30","nuclei":"1H","solvent":"CH3CN","parMode":0,"pparMode":0,"timestamp":"2024-07-28T17:15:19.760325Z"},{"file":"batch1-18\\1001002\\pdata\\1\\","type":"Dataset","path":"","name":"batch1-18","procno":1,"expno":1001002,"title":"batch1-18\n64: [Yittrium(III) trifluoromethanesulfonate, 4,4'-(9H-Fluorene-9,9-diyl)dianiline, 6-Methylpyridine-2-carboxaldehyde]\nMULTISUPPDC_f","date":"2024-02-29T13:38:39Z","dataType":null,"specType":"DEPT45","sf":20.150719396,"pulProg":"deptsp45","nuclei":"13C","solvent":"CH3CN","parMode":0,"pparMode":0,"timestamp":"2024-07-28T17:15:21.378856Z"},{"file":"batch1-19\\10\\pdata\\1\\","type":"Dataset","path":"","name":"batch1-19","procno":1,"expno":10,"title":"batch1-19\n65: [Yittrium(III) trifluoromethanesulfonate, Naphthalene-1,8-diamine, 6-Methoxypyridine-2-carbaldehyde]\nMULTISUPPDC_f","date":"2024-02-29T13:57:18Z","dataType":null,"specType":"","sf":80.130376615,"pulProg":"noesycpdcgpps1d","nuclei":"1H","solvent":"CH3CN","parMode":0,"pparMode":0,"timestamp":"2024-07-28T17:15:17.862765Z"},{"file":"batch1-19\\1001001\\pdata\\1\\","type":"Dataset","path":"","name":"batch1-19","procno":1,"expno":1001001,"title":"batch1-19\n65: [Yittrium(III) trifluoromethanesulfonate, Naphthalene-1,8-diamine, 6-Methoxypyridine-2-carbaldehyde]\nMULTISUPPDC_f\nPeaks for suppression at (in Hz):\n237.03; 169.33; 100.79; ","date":"2024-02-29T13:49:33Z","dataType":null,"specType":"PROTON","sf":80.130494803,"pulProg":"zg30","nuclei":"1H","solvent":"CH3CN","parMode":0,"pparMode":0,"timestamp":"2024-07-28T17:15:09.233117Z"},{"file":"batch1-19\\1001002\\pdata\\1\\","type":"Dataset","path":"","name":"batch1-19","procno":1,"expno":1001002,"title":"batch1-19\n65: [Yittrium(III) trifluoromethanesulfonate, Naphthalene-1,8-diamine, 6-Methoxypyridine-2-carbaldehyde]\nMULTISUPPDC_f","date":"2024-02-29T13:49:44Z","dataType":null,"specType":"DEPT45","sf":20.150719396,"pulProg":"deptsp45","nuclei":"13C","solvent":"CH3CN","parMode":0,"pparMode":0,"timestamp":"2024-07-28T17:15:20.636353Z"},{"file":"batch1-20\\10\\pdata\\1\\","type":"Dataset","path":"","name":"batch1-20","procno":1,"expno":10,"title":"batch1-20\n66: [Yittrium(III) trifluoromethanesulfonate, 4,4'-(9H-Fluorene-9,9-diyl)dianiline, 6-Methoxypyridine-2-carbaldehyde]\nMULTISUPPDC_f","date":"2024-02-29T14:08:25Z","dataType":null,"specType":"","sf":80.130376615,"pulProg":"noesycpdcgpps1d","nuclei":"1H","solvent":"CH3CN","parMode":0,"pparMode":0,"timestamp":"2024-07-28T17:15:16.319284Z"},{"file":"batch1-20\\1001001\\pdata\\1\\","type":"Dataset","path":"","name":"batch1-20","procno":1,"expno":1001001,"title":"batch1-20\n66: [Yittrium(III) trifluoromethanesulfonate, 4,4'-(9H-Fluorene-9,9-diyl)dianiline, 6-Methoxypyridine-2-carbaldehyde]\nMULTISUPPDC_f\nPeaks for suppression at (in Hz):\n238.10; 170.35; 101.85; ","date":"2024-02-29T14:00:38Z","dataType":null,"specType":"PROTON","sf":80.130494803,"pulProg":"zg30","nuclei":"1H","solvent":"CH3CN","parMode":0,"pparMode":0,"timestamp":"2024-07-28T17:15:22.079351Z"},{"file":"batch1-20\\1001002\\pdata\\1\\","type":"Dataset","path":"","name":"batch1-20","procno":1,"expno":1001002,"title":"batch1-20\n66: [Yittrium(III) trifluoromethanesulfonate, 4,4'-(9H-Fluorene-9,9-diyl)dianiline, 6-Methoxypyridine-2-carbaldehyde]\nMULTISUPPDC_f","date":"2024-02-29T14:00:50Z","dataType":null,"specType":"DEPT45","sf":20.150719396,"pulProg":"deptsp45","nuclei":"13C","solvent":"CH3CN","parMode":0,"pparMode":0,"timestamp":"2024-07-28T17:15:19.294207Z"},{"file":"batch1-21\\10\\pdata\\1\\","type":"Dataset","path":"","name":"batch1-21","procno":1,"expno":10,"title":"batch1-21\n67: [Yittrium(III) trifluoromethanesulfonate, 5-Methylpicolinaldehyde, 4,4'-Methylenedianiline]\nMULTISUPPDC_f","date":"2024-02-29T14:19:31Z","dataType":null,"specType":"","sf":80.130376615,"pulProg":"noesycpdcgpps1d","nuclei":"1H","solvent":"CH3CN","parMode":0,"pparMode":0,"timestamp":"2024-07-28T17:15:19.774476Z"},{"file":"batch1-21\\1001001\\pdata\\1\\","type":"Dataset","path":"","name":"batch1-21","procno":1,"expno":1001001,"title":"batch1-21\n67: [Yittrium(III) trifluoromethanesulfonate, 5-Methylpicolinaldehyde, 4,4'-Methylenedianiline]\nMULTISUPPDC_f\nPeaks for suppression at (in Hz):\n237.20; 169.48; 100.96; ","date":"2024-02-29T14:11:44Z","dataType":null,"specType":"PROTON","sf":80.130494803,"pulProg":"zg30","nuclei":"1H","solvent":"CH3CN","parMode":0,"pparMode":0,"timestamp":"2024-07-28T17:15:21.391499Z"},{"file":"batch1-21\\1001002\\pdata\\1\\","type":"Dataset","path":"","name":"batch1-21","procno":1,"expno":1001002,"title":"batch1-21\n67: [Yittrium(III) trifluoromethanesulfonate, 5-Methylpicolinaldehyde, 4,4'-Methylenedianiline]\nMULTISUPPDC_f","date":"2024-02-29T14:11:55Z","dataType":null,"specType":"DEPT45","sf":20.150719396,"pulProg":"deptsp45","nuclei":"13C","solvent":"CH3CN","parMode":0,"pparMode":0,"timestamp":"2024-07-28T17:15:17.870381Z"},{"file":"batch1-22\\10\\pdata\\1\\","type":"Dataset","path":"","name":"batch1-22","procno":1,"expno":10,"title":"batch1-22\n68: [Yittrium(III) trifluoromethanesulfonate, 5-Methylpicolinaldehyde, 2,2'-(Ethane-1,2-diylbis(oxy))diethanamine]\nMULTISUPPDC_f","date":"2024-02-29T14:30:36Z","dataType":null,"specType":"","sf":80.130376615,"pulProg":"noesycpdcgpps1d","nuclei":"1H","solvent":"CH3CN","parMode":0,"pparMode":0,"timestamp":"2024-07-28T17:15:09.237870Z"},{"file":"batch1-22\\1001001\\pdata\\1\\","type":"Dataset","path":"","name":"batch1-22","procno":1,"expno":1001001,"title":"batch1-22\n68: [Yittrium(III) trifluoromethanesulfonate, 5-Methylpicolinaldehyde, 2,2'-(Ethane-1,2-diylbis(oxy))diethanamine]\nMULTISUPPDC_f\nPeaks for suppression at (in Hz):\n447.67; 236.97; 169.23; 100.73; ","date":"2024-02-29T14:22:49Z","dataType":null,"specType":"PROTON","sf":80.130494803,"pulProg":"zg30","nuclei":"1H","solvent":"CH3CN","parMode":0,"pparMode":0,"timestamp":"2024-07-28T17:15:20.648234Z"},{"file":"batch1-22\\1001002\\pdata\\1\\","type":"Dataset","path":"","name":"batch1-22","procno":1,"expno":1001002,"title":"batch1-22\n68: [Yittrium(III) trifluoromethanesulfonate, 5-Methylpicolinaldehyde, 2,2'-(Ethane-1,2-diylbis(oxy))diethanamine]\nMULTISUPPDC_f\nPeaks for suppression at (in Hz):\n20.49; ","date":"2024-02-29T14:23:01Z","dataType":null,"specType":"DEPT45","sf":20.150719396,"pulProg":"deptsp45","nuclei":"13C","solvent":"CH3CN","parMode":0,"pparMode":0,"timestamp":"2024-07-28T17:15:16.328985Z"},{"file":"batch1-23\\10\\pdata\\1\\","type":"Dataset","path":"","name":"batch1-23","procno":1,"expno":10,"title":"batch1-23\n69: [Yittrium(III) trifluoromethanesulfonate, 5-Methylpicolinaldehyde, 4,4'-Oxydianiline]\nMULTISUPPDC_f","date":"2024-02-29T14:41:48Z","dataType":null,"specType":"","sf":80.130376615,"pulProg":"noesycpdcgpps1d","nuclei":"1H","solvent":"CH3CN","parMode":0,"pparMode":0,"timestamp":"2024-07-28T17:15:22.084541Z"},{"file":"batch1-23\\1001001\\pdata\\1\\","type":"Dataset","path":"","name":"batch1-23","procno":1,"expno":1001001,"title":"batch1-23\n69: [Yittrium(III) trifluoromethanesulfonate, 5-Methylpicolinaldehyde, 4,4'-Oxydianiline]\nMULTISUPPDC_f\nPeaks for suppression at (in Hz):\n236.62; 168.88; 100.38; ","date":"2024-02-29T14:34:01Z","dataType":null,"specType":"PROTON","sf":80.130494803,"pulProg":"zg30","nuclei":"1H","solvent":"CH3CN","parMode":0,"pparMode":0,"timestamp":"2024-07-28T17:15:19.304177Z"},{"file":"batch1-23\\1001002\\pdata\\1\\","type":"Dataset","path":"","name":"batch1-23","procno":1,"expno":1001002,"title":"batch1-23\n69: [Yittrium(III) trifluoromethanesulfonate, 5-Methylpicolinaldehyde, 4,4'-Oxydianiline]\nMULTISUPPDC_f","date":"2024-02-29T14:34:14Z","dataType":null,"specType":"DEPT45","sf":20.150719396,"pulProg":"deptsp45","nuclei":"13C","solvent":"CH3CN","parMode":0,"pparMode":0,"timestamp":"2024-07-28T17:15:19.785587Z"},{"file":"batch1-24\\10\\pdata\\1\\","type":"Dataset","path":"","name":"batch1-24","procno":1,"expno":10,"title":"batch1-24\n70: [Yittrium(III) trifluoromethanesulfonate, 5-Methylpicolinaldehyde, Naphthalene-1,8-diamine]\nMULTISUPPDC_f","date":"2024-02-29T14:52:54Z","dataType":null,"specType":"","sf":80.130376615,"pulProg":"noesycpdcgpps1d","nuclei":"1H","solvent":"CH3CN","parMode":0,"pparMode":0,"timestamp":"2024-07-28T17:15:21.411793Z"},{"file":"batch1-24\\1001001\\pdata\\1\\","type":"Dataset","path":"","name":"batch1-24","procno":1,"expno":1001001,"title":"batch1-24\n70: [Yittrium(III) trifluoromethanesulfonate, 5-Methylpicolinaldehyde, Naphthalene-1,8-diamine]\nMULTISUPPDC_f\nPeaks for suppression at (in Hz):\n235.94; 168.20; 99.70; ","date":"2024-02-29T14:45:07Z","dataType":null,"specType":"PROTON","sf":80.130494803,"pulProg":"zg30","nuclei":"1H","solvent":"CH3CN","parMode":0,"pparMode":0,"timestamp":"2024-07-28T17:15:17.879621Z"},{"file":"batch1-24\\1001002\\pdata\\1\\","type":"Dataset","path":"","name":"batch1-24","procno":1,"expno":1001002,"title":"batch1-24\n70: [Yittrium(III) trifluoromethanesulfonate, 5-Methylpicolinaldehyde, Naphthalene-1,8-diamine]\nMULTISUPPDC_f","date":"2024-02-29T14:45:19Z","dataType":null,"specType":"DEPT45","sf":20.150719396,"pulProg":"deptsp45","nuclei":"13C","solvent":"CH3CN","parMode":0,"pparMode":0,"timestamp":"2024-07-28T17:15:09.267739Z"},{"file":"batch1-25\\10\\pdata\\1\\","type":"Dataset","path":"","name":"batch1-25","procno":1,"expno":10,"title":"batch1-25\n71: [Yittrium(III) trifluoromethanesulfonate, 5-Methylpicolinaldehyde, 4,4'-(9H-Fluorene-9,9-diyl)dianiline]\nMULTISUPPDC_f","date":"2024-02-29T15:04:01Z","dataType":null,"specType":"","sf":80.130376615,"pulProg":"noesycpdcgpps1d","nuclei":"1H","solvent":"CH3CN","parMode":0,"pparMode":0,"timestamp":"2024-07-28T17:15:20.658560Z"},{"file":"batch1-25\\1001001\\pdata\\1\\","type":"Dataset","path":"","name":"batch1-25","procno":1,"expno":1001001,"title":"batch1-25\n71: [Yittrium(III) trifluoromethanesulfonate, 5-Methylpicolinaldehyde, 4,4'-(9H-Fluorene-9,9-diyl)dianiline]\nMULTISUPPDC_f\nPeaks for suppression at (in Hz):\n236.72; 168.97; 100.48; ","date":"2024-02-29T14:56:14Z","dataType":null,"specType":"PROTON","sf":80.130494803,"pulProg":"zg30","nuclei":"1H","solvent":"CH3CN","parMode":0,"pparMode":0,"timestamp":"2024-07-28T17:15:16.340532Z"},{"file":"batch1-25\\1001002\\pdata\\1\\","type":"Dataset","path":"","name":"batch1-25","procno":1,"expno":1001002,"title":"batch1-25\n71: [Yittrium(III) trifluoromethanesulfonate, 5-Methylpicolinaldehyde, 4,4'-(9H-Fluorene-9,9-diyl)dianiline]\nMULTISUPPDC_f","date":"2024-02-29T14:56:26Z","dataType":null,"specType":"DEPT45","sf":20.150719396,"pulProg":"deptsp45","nuclei":"13C","solvent":"CH3CN","parMode":0,"pparMode":0,"timestamp":"2024-07-28T17:15:22.090315Z"},{"file":"batch1-26\\10\\pdata\\1\\","type":"Dataset","path":"","name":"batch1-26","procno":1,"expno":10,"title":"batch1-26\n72: [Yittrium(III) trifluoromethanesulfonate, 1,3-Benzenedimethanamine, 6-Methylpyridine-2-carboxaldehyde]\nMULTISUPPDC_f","date":"2024-02-29T15:15:07Z","dataType":null,"specType":"","sf":80.130376615,"pulProg":"noesycpdcgpps1d","nuclei":"1H","solvent":"CH3CN","parMode":0,"pparMode":0,"timestamp":"2024-07-28T17:15:19.313840Z"},{"file":"batch1-26\\1001001\\pdata\\1\\","type":"Dataset","path":"","name":"batch1-26","procno":1,"expno":1001001,"title":"batch1-26\n72: [Yittrium(III) trifluoromethanesulfonate, 1,3-Benzenedimethanamine, 6-Methylpyridine-2-carboxaldehyde]\nMULTISUPPDC_f\nPeaks for suppression at (in Hz):\n237.57; 169.85; 101.33; ","date":"2024-02-29T15:07:20Z","dataType":null,"specType":"PROTON","sf":80.130494803,"pulProg":"zg30","nuclei":"1H","solvent":"CH3CN","parMode":0,"pparMode":0,"timestamp":"2024-07-28T17:15:19.798124Z"},{"file":"batch1-26\\1001002\\pdata\\1\\","type":"Dataset","path":"","name":"batch1-26","procno":1,"expno":1001002,"title":"batch1-26\n72: [Yittrium(III) trifluoromethanesulfonate, 1,3-Benzenedimethanamine, 6-Methylpyridine-2-carboxaldehyde]\nMULTISUPPDC_f","date":"2024-02-29T15:07:32Z","dataType":null,"specType":"DEPT45","sf":20.150719396,"pulProg":"deptsp45","nuclei":"13C","solvent":"CH3CN","parMode":0,"pparMode":0,"timestamp":"2024-07-28T17:15:21.427171Z"},{"file":"batch1-28\\10\\pdata\\1\\","type":"Dataset","path":"","name":"batch1-28","procno":1,"expno":10,"title":"batch1-28\n74: [Yittrium(III) trifluoromethanesulfonate, 1,3-Benzenedimethanamine, 5-Methylpicolinaldehyde]\nMULTISUPPDC_f","date":"2024-02-29T15:37:23Z","dataType":null,"specType":"","sf":80.130376615,"pulProg":"noesycpdcgpps1d","nuclei":"1H","solvent":"CH3CN","parMode":0,"pparMode":0,"timestamp":"2024-07-28T17:15:17.885696Z"},{"file":"batch1-28\\1001001\\pdata\\1\\","type":"Dataset","path":"","name":"batch1-28","procno":1,"expno":1001001,"title":"batch1-28\n74: [Yittrium(III) trifluoromethanesulfonate, 1,3-Benzenedimethanamine, 5-Methylpicolinaldehyde]\nMULTISUPPDC_f\nPeaks for suppression at (in Hz):\n237.18; 169.43; 100.94; ","date":"2024-02-29T15:29:34Z","dataType":null,"specType":"PROTON","sf":80.130494803,"pulProg":"zg30","nuclei":"1H","solvent":"CH3CN","parMode":0,"pparMode":0,"timestamp":"2024-07-28T17:15:09.281399Z"},{"file":"batch1-28\\1001002\\pdata\\1\\","type":"Dataset","path":"","name":"batch1-28","procno":1,"expno":1001002,"title":"batch1-28\n74: [Yittrium(III) trifluoromethanesulfonate, 1,3-Benzenedimethanamine, 5-Methylpicolinaldehyde]\nMULTISUPPDC_f","date":"2024-02-29T15:29:47Z","dataType":null,"specType":"DEPT45","sf":20.150719396,"pulProg":"deptsp45","nuclei":"13C","solvent":"CH3CN","parMode":0,"pparMode":0,"timestamp":"2024-07-28T17:15:20.669675Z"},{"file":"batch1-30\\10\\pdata\\1\\","type":"Dataset","path":"","name":"batch1-30","procno":1,"expno":10,"title":"batch1-30\n76: [Yittrium(III) trifluoromethanesulfonate, 1-Methyl-2-imidazolecarboxaldehyde, 2,2'-(Ethane-1,2-diylbis(oxy))diethanamine]\nMULTISUPPDC_f","date":"2024-02-29T15:59:39Z","dataType":null,"specType":"","sf":80.130376615,"pulProg":"noesycpdcgpps1d","nuclei":"1H","solvent":"CH3CN","parMode":0,"pparMode":0,"timestamp":"2024-07-28T17:15:16.352327Z"},{"file":"batch1-30\\1001001\\pdata\\1\\","type":"Dataset","path":"","name":"batch1-30","procno":1,"expno":1001001,"title":"batch1-30\n76: [Yittrium(III) trifluoromethanesulfonate, 1-Methyl-2-imidazolecarboxaldehyde, 2,2'-(Ethane-1,2-diylbis(oxy))diethanamine]\nMULTISUPPDC_f\nPeaks for suppression at (in Hz):\n451.89; 241.11; 173.37; 104.87; ","date":"2024-02-29T15:51:51Z","dataType":null,"specType":"PROTON","sf":80.130494803,"pulProg":"zg30","nuclei":"1H","solvent":"CH3CN","parMode":0,"pparMode":0,"timestamp":"2024-07-28T17:15:22.099175Z"},{"file":"batch1-30\\1001002\\pdata\\1\\","type":"Dataset","path":"","name":"batch1-30","procno":1,"expno":1001002,"title":"batch1-30\n76: [Yittrium(III) trifluoromethanesulfonate, 1-Methyl-2-imidazolecarboxaldehyde, 2,2'-(Ethane-1,2-diylbis(oxy))diethanamine]\nMULTISUPPDC_f\nPeaks for suppression at (in Hz):\n21.47; ","date":"2024-02-29T15:52:03Z","dataType":null,"specType":"DEPT45","sf":20.150719396,"pulProg":"deptsp45","nuclei":"13C","solvent":"CH3CN","parMode":0,"pparMode":0,"timestamp":"2024-07-28T17:15:19.321002Z"},{"file":"batch1-31\\10\\pdata\\1\\","type":"Dataset","path":"","name":"batch1-31","procno":1,"expno":10,"title":"batch1-31\n77: [Yittrium(III) trifluoromethanesulfonate, 1-Methyl-2-imidazolecarboxaldehyde, 4,4'-Oxydianiline]\nMULTISUPPDC_f","date":"2024-02-29T16:10:45Z","dataType":null,"specType":"","sf":80.130376615,"pulProg":"noesycpdcgpps1d","nuclei":"1H","solvent":"CH3CN","parMode":0,"pparMode":0,"timestamp":"2024-07-28T17:15:19.808791Z"},{"file":"batch1-31\\1001001\\pdata\\1\\","type":"Dataset","path":"","name":"batch1-31","procno":1,"expno":1001001,"title":"batch1-31\n77: [Yittrium(III) trifluoromethanesulfonate, 1-Methyl-2-imidazolecarboxaldehyde, 4,4'-Oxydianiline]\nMULTISUPPDC_f\nPeaks for suppression at (in Hz):\n236.98; 169.24; 100.74; ","date":"2024-02-29T16:02:58Z","dataType":null,"specType":"PROTON","sf":80.130494803,"pulProg":"zg30","nuclei":"1H","solvent":"CH3CN","parMode":0,"pparMode":0,"timestamp":"2024-07-28T17:15:21.444763Z"},{"file":"batch1-31\\1001002\\pdata\\1\\","type":"Dataset","path":"","name":"batch1-31","procno":1,"expno":1001002,"title":"batch1-31\n77: [Yittrium(III) trifluoromethanesulfonate, 1-Methyl-2-imidazolecarboxaldehyde, 4,4'-Oxydianiline]\nMULTISUPPDC_f","date":"2024-02-29T16:03:10Z","dataType":null,"specType":"DEPT45","sf":20.150719396,"pulProg":"deptsp45","nuclei":"13C","solvent":"CH3CN","parMode":0,"pparMode":0,"timestamp":"2024-07-28T17:15:17.890674Z"},{"file":"batch1-32\\10\\pdata\\1\\","type":"Dataset","path":"","name":"batch1-32","procno":1,"expno":10,"title":"batch1-32\n78: [Yittrium(III) trifluoromethanesulfonate, 2,2'-(Ethane-1,2-diyl)dianiline, 6-Methylpyridine-2-carboxaldehyde]\nMULTISUPPDC_f","date":"2024-02-29T16:21:48Z","dataType":null,"specType":"","sf":80.130376615,"pulProg":"noesycpdcgpps1d","nuclei":"1H","solvent":"CH3CN","parMode":0,"pparMode":0,"timestamp":"2024-07-28T17:15:09.290136Z"},{"file":"batch1-32\\1001001\\pdata\\1\\","type":"Dataset","path":"","name":"batch1-32","procno":1,"expno":1001001,"title":"batch1-32\n78: [Yittrium(III) trifluoromethanesulfonate, 2,2'-(Ethane-1,2-diyl)dianiline, 6-Methylpyridine-2-carboxaldehyde]\nMULTISUPPDC_f\nPeaks for suppression at (in Hz):\n237.26; 169.52; 101.01; ","date":"2024-02-29T16:14:04Z","dataType":null,"specType":"PROTON","sf":80.130494803,"pulProg":"zg30","nuclei":"1H","solvent":"CH3CN","parMode":0,"pparMode":0,"timestamp":"2024-07-28T17:15:20.674708Z"},{"file":"batch1-32\\1001002\\pdata\\1\\","type":"Dataset","path":"","name":"batch1-32","procno":1,"expno":1001002,"title":"batch1-32\n78: [Yittrium(III) trifluoromethanesulfonate, 2,2'-(Ethane-1,2-diyl)dianiline, 6-Methylpyridine-2-carboxaldehyde]\nMULTISUPPDC_f","date":"2024-02-29T16:14:15Z","dataType":null,"specType":"DEPT45","sf":20.150719396,"pulProg":"deptsp45","nuclei":"13C","solvent":"CH3CN","parMode":0,"pparMode":0,"timestamp":"2024-07-28T17:15:16.364139Z"},{"file":"batch1-33\\10\\pdata\\1\\","type":"Dataset","path":"","name":"batch1-33","procno":1,"expno":10,"title":"batch1-33\n79: [Yittrium(III) trifluoromethanesulfonate, 1-Methyl-2-imidazolecarboxaldehyde, Naphthalene-1,8-diamine]\nMULTISUPPDC_f","date":"2024-02-29T16:32:54Z","dataType":null,"specType":"","sf":80.130376615,"pulProg":"noesycpdcgpps1d","nuclei":"1H","solvent":"CH3CN","parMode":0,"pparMode":0,"timestamp":"2024-07-28T17:15:22.104358Z"},{"file":"batch1-33\\1001001\\pdata\\1\\","type":"Dataset","path":"","name":"batch1-33","procno":1,"expno":1001001,"title":"batch1-33\n79: [Yittrium(III) trifluoromethanesulfonate, 1-Methyl-2-imidazolecarboxaldehyde, Naphthalene-1,8-diamine]\nMULTISUPPDC_f\nPeaks for suppression at (in Hz):\n169.79; ","date":"2024-02-29T16:25:08Z","dataType":null,"specType":"PROTON","sf":80.130494803,"pulProg":"zg30","nuclei":"1H","solvent":"CH3CN","parMode":0,"pparMode":0,"timestamp":"2024-07-28T17:15:19.326169Z"},{"file":"batch1-33\\1001002\\pdata\\1\\","type":"Dataset","path":"","name":"batch1-33","procno":1,"expno":1001002,"title":"batch1-33\n79: [Yittrium(III) trifluoromethanesulfonate, 1-Methyl-2-imidazolecarboxaldehyde, Naphthalene-1,8-diamine]\nMULTISUPPDC_f","date":"2024-02-29T16:25:19Z","dataType":null,"specType":"DEPT45","sf":20.150719396,"pulProg":"deptsp45","nuclei":"13C","solvent":"CH3CN","parMode":0,"pparMode":0,"timestamp":"2024-07-28T17:15:19.820376Z"},{"file":"batch1-34\\10\\pdata\\1\\","type":"Dataset","path":"","name":"batch1-34","procno":1,"expno":10,"title":"batch1-34\n80: [Yittrium(III) trifluoromethanesulfonate, 1-Methyl-2-imidazolecarboxaldehyde, 4,4'-(9H-Fluorene-9,9-diyl)dianiline]\nMULTISUPPDC_f","date":"2024-02-29T16:44:00Z","dataType":null,"specType":"","sf":80.130376615,"pulProg":"noesycpdcgpps1d","nuclei":"1H","solvent":"CH3CN","parMode":0,"pparMode":0,"timestamp":"2024-07-28T17:15:21.452290Z"},{"file":"batch1-34\\1001001\\pdata\\1\\","type":"Dataset","path":"","name":"batch1-34","procno":1,"expno":1001001,"title":"batch1-34\n80: [Yittrium(III) trifluoromethanesulfonate, 1-Methyl-2-imidazolecarboxaldehyde, 4,4'-(9H-Fluorene-9,9-diyl)dianiline]\nMULTISUPPDC_f\nPeaks for suppression at (in Hz):\n242.95; 175.25; 106.71; ","date":"2024-02-29T16:36:14Z","dataType":null,"specType":"PROTON","sf":80.130494803,"pulProg":"zg30","nuclei":"1H","solvent":"CH3CN","parMode":0,"pparMode":0,"timestamp":"2024-07-28T17:15:17.898730Z"},{"file":"batch1-34\\1001002\\pdata\\1\\","type":"Dataset","path":"","name":"batch1-34","procno":1,"expno":1001002,"title":"batch1-34\n80: [Yittrium(III) trifluoromethanesulfonate, 1-Methyl-2-imidazolecarboxaldehyde, 4,4'-(9H-Fluorene-9,9-diyl)dianiline]\nMULTISUPPDC_f\nPeaks for suppression at (in Hz):\n21.14; ","date":"2024-02-29T16:36:26Z","dataType":null,"specType":"DEPT45","sf":20.150719396,"pulProg":"deptsp45","nuclei":"13C","solvent":"CH3CN","parMode":0,"pparMode":0,"timestamp":"2024-07-28T17:15:09.298581Z"},{"file":"batch1-35\\10\\pdata\\1\\","type":"Dataset","path":"","name":"batch1-35","procno":1,"expno":10,"title":"batch1-35\n81: [Yittrium(III) trifluoromethanesulfonate, 2,2'-(Ethane-1,2-diyl)dianiline, 6-Methoxypyridine-2-carbaldehyde]\nMULTISUPPDC_f","date":"2024-02-29T17:19:22Z","dataType":null,"specType":"","sf":80.130376615,"pulProg":"noesycpdcgpps1d","nuclei":"1H","solvent":"CH3CN","parMode":0,"pparMode":0,"timestamp":"2024-07-28T17:15:20.680303Z"},{"file":"batch1-35\\1001001\\pdata\\1\\","type":"Dataset","path":"","name":"batch1-35","procno":1,"expno":1001001,"title":"batch1-35\n81: [Yittrium(III) trifluoromethanesulfonate, 2,2'-(Ethane-1,2-diyl)dianiline, 6-Methoxypyridine-2-carbaldehyde]\nMULTISUPPDC_f\nPeaks for suppression at (in Hz):\n237.83; 170.10; 101.59; ","date":"2024-02-29T17:11:35Z","dataType":null,"specType":"PROTON","sf":80.130494803,"pulProg":"zg30","nuclei":"1H","solvent":"CH3CN","parMode":0,"pparMode":0,"timestamp":"2024-07-28T17:15:16.374894Z"},{"file":"batch1-35\\1001002\\pdata\\1\\","type":"Dataset","path":"","name":"batch1-35","procno":1,"expno":1001002,"title":"batch1-35\n81: [Yittrium(III) trifluoromethanesulfonate, 2,2'-(Ethane-1,2-diyl)dianiline, 6-Methoxypyridine-2-carbaldehyde]\nMULTISUPPDC_f","date":"2024-02-29T17:11:46Z","dataType":null,"specType":"DEPT45","sf":20.150719396,"pulProg":"deptsp45","nuclei":"13C","solvent":"CH3CN","parMode":0,"pparMode":0,"timestamp":"2024-07-28T17:15:22.109829Z"},{"file":"batch1-36\\10\\pdata\\1\\","type":"Dataset","path":"","name":"batch1-36","procno":1,"expno":10,"title":"batch1-36\n82: [Yittrium(III) trifluoromethanesulfonate, 2,2'-(Ethane-1,2-diyl)dianiline, 5-Methylpicolinaldehyde]\nMULTISUPPDC_f","date":"2024-02-29T17:30:27Z","dataType":null,"specType":"","sf":80.130376615,"pulProg":"noesycpdcgpps1d","nuclei":"1H","solvent":"CH3CN","parMode":0,"pparMode":0,"timestamp":"2024-07-28T17:15:19.335143Z"},{"file":"batch1-36\\1001001\\pdata\\1\\","type":"Dataset","path":"","name":"batch1-36","procno":1,"expno":1001001,"title":"batch1-36\n82: [Yittrium(III) trifluoromethanesulfonate, 2,2'-(Ethane-1,2-diyl)dianiline, 5-Methylpicolinaldehyde]\nMULTISUPPDC_f\nPeaks for suppression at (in Hz):\n235.12; 167.38; 98.88; ","date":"2024-02-29T17:22:42Z","dataType":null,"specType":"PROTON","sf":80.130494803,"pulProg":"zg30","nuclei":"1H","solvent":"CH3CN","parMode":0,"pparMode":0,"timestamp":"2024-07-28T17:15:19.833204Z"},{"file":"batch1-36\\1001002\\pdata\\1\\","type":"Dataset","path":"","name":"batch1-36","procno":1,"expno":1001002,"title":"batch1-36\n82: [Yittrium(III) trifluoromethanesulfonate, 2,2'-(Ethane-1,2-diyl)dianiline, 5-Methylpicolinaldehyde]\nMULTISUPPDC_f","date":"2024-02-29T17:22:53Z","dataType":null,"specType":"DEPT45","sf":20.150719396,"pulProg":"deptsp45","nuclei":"13C","solvent":"CH3CN","parMode":0,"pparMode":0,"timestamp":"2024-07-28T17:15:21.468197Z"},{"file":"batch1-37\\10\\pdata\\1\\","type":"Dataset","path":"","name":"batch1-37","procno":1,"expno":10,"title":"batch1-37\n83: [Yittrium(III) trifluoromethanesulfonate, 1-Methyl-2-imidazolecarboxaldehyde, 1,3-Benzenedimethanamine]\nMULTISUPPDC_f","date":"2024-02-29T17:41:34Z","dataType":null,"specType":"","sf":80.130376615,"pulProg":"noesycpdcgpps1d","nuclei":"1H","solvent":"CH3CN","parMode":0,"pparMode":0,"timestamp":"2024-07-28T17:15:17.902718Z"},{"file":"batch1-37\\1001001\\pdata\\1\\","type":"Dataset","path":"","name":"batch1-37","procno":1,"expno":1001001,"title":"batch1-37\n83: [Yittrium(III) trifluoromethanesulfonate, 1-Methyl-2-imidazolecarboxaldehyde, 1,3-Benzenedimethanamine]\nMULTISUPPDC_f\nPeaks for suppression at (in Hz):\n237.82; 170.08; 101.58; ","date":"2024-02-29T17:33:46Z","dataType":null,"specType":"PROTON","sf":80.130494803,"pulProg":"zg30","nuclei":"1H","solvent":"CH3CN","parMode":0,"pparMode":0,"timestamp":"2024-07-28T17:15:09.322244Z"},{"file":"batch1-37\\1001002\\pdata\\1\\","type":"Dataset","path":"","name":"batch1-37","procno":1,"expno":1001002,"title":"batch1-37\n83: [Yittrium(III) trifluoromethanesulfonate, 1-Methyl-2-imidazolecarboxaldehyde, 1,3-Benzenedimethanamine]\nMULTISUPPDC_f","date":"2024-02-29T17:33:58Z","dataType":null,"specType":"DEPT45","sf":20.150719396,"pulProg":"deptsp45","nuclei":"13C","solvent":"CH3CN","parMode":0,"pparMode":0,"timestamp":"2024-07-28T17:15:20.685288Z"},{"file":"batch1-38\\10\\pdata\\1\\","type":"Dataset","path":"","name":"batch1-38","procno":1,"expno":10,"title":"batch1-38\n84: [Yittrium(III) trifluoromethanesulfonate, 2,2'-(Ethane-1,2-diyl)dianiline, 1-Methyl-2-imidazolecarboxaldehyde]\nMULTISUPPDC_f","date":"2024-02-29T17:52:42Z","dataType":null,"specType":"","sf":80.130376615,"pulProg":"noesycpdcgpps1d","nuclei":"1H","solvent":"CH3CN","parMode":0,"pparMode":0,"timestamp":"2024-07-28T17:15:16.386685Z"},{"file":"batch1-38\\1001001\\pdata\\1\\","type":"Dataset","path":"","name":"batch1-38","procno":1,"expno":1001001,"title":"batch1-38\n84: [Yittrium(III) trifluoromethanesulfonate, 2,2'-(Ethane-1,2-diyl)dianiline, 1-Methyl-2-imidazolecarboxaldehyde]\nMULTISUPPDC_f\nPeaks for suppression at (in Hz):\n241.31; 173.64; 105.07; ","date":"2024-02-29T17:44:56Z","dataType":null,"specType":"PROTON","sf":80.130494803,"pulProg":"zg30","nuclei":"1H","solvent":"CH3CN","parMode":0,"pparMode":0,"timestamp":"2024-07-28T17:15:22.113751Z"},{"file":"batch1-38\\1001002\\pdata\\1\\","type":"Dataset","path":"","name":"batch1-38","procno":1,"expno":1001002,"title":"batch1-38\n84: [Yittrium(III) trifluoromethanesulfonate, 2,2'-(Ethane-1,2-diyl)dianiline, 1-Methyl-2-imidazolecarboxaldehyde]\nMULTISUPPDC_f\nPeaks for suppression at (in Hz):\n20.61; ","date":"2024-02-29T17:45:07Z","dataType":null,"specType":"DEPT45","sf":20.150719396,"pulProg":"deptsp45","nuclei":"13C","solvent":"CH3CN","parMode":0,"pparMode":0,"timestamp":"2024-07-28T17:15:19.345167Z"},{"file":"batch1-39\\10\\pdata\\1\\","type":"Dataset","path":"","name":"batch1-39","procno":1,"expno":10,"title":"batch1-39\n85: [4-Formyl-2-methylthiazole, Zinc tetrafluoroborate, 4,4'-Methylenedianiline]\nMULTISUPPDC_f","date":"2024-02-29T18:03:47Z","dataType":null,"specType":"","sf":80.130376615,"pulProg":"noesycpdcgpps1d","nuclei":"1H","solvent":"CH3CN","parMode":0,"pparMode":0,"timestamp":"2024-07-28T17:15:19.855097Z"},{"file":"batch1-39\\1001001\\pdata\\1\\","type":"Dataset","path":"","name":"batch1-39","procno":1,"expno":1001001,"title":"batch1-39\n85: [4-Formyl-2-methylthiazole, Zinc tetrafluoroborate, 4,4'-Methylenedianiline]\nMULTISUPPDC_f\nPeaks for suppression at (in Hz):\n236.51; 185.15; 168.78; 100.27; ","date":"2024-02-29T17:56:02Z","dataType":null,"specType":"PROTON","sf":80.130494803,"pulProg":"zg30","nuclei":"1H","solvent":"CH3CN","parMode":0,"pparMode":0,"timestamp":"2024-07-28T17:15:21.481702Z"},{"file":"batch1-39\\1001002\\pdata\\1\\","type":"Dataset","path":"","name":"batch1-39","procno":1,"expno":1001002,"title":"batch1-39\n85: [4-Formyl-2-methylthiazole, Zinc tetrafluoroborate, 4,4'-Methylenedianiline]\nMULTISUPPDC_f","date":"2024-02-29T17:56:13Z","dataType":null,"specType":"DEPT45","sf":20.150719396,"pulProg":"deptsp45","nuclei":"13C","solvent":"CH3CN","parMode":0,"pparMode":0,"timestamp":"2024-07-28T17:15:17.907519Z"},{"file":"batch1-41\\10\\pdata\\1\\","type":"Dataset","path":"","name":"batch1-41","procno":1,"expno":10,"title":"batch1-41\n87: [4-Formyl-2-methylthiazole, Zinc tetrafluoroborate, 4,4'-Oxydianiline]\nMULTISUPPDC_f","date":"2024-02-29T18:26:04Z","dataType":null,"specType":"","sf":80.130376615,"pulProg":"noesycpdcgpps1d","nuclei":"1H","solvent":"CH3CN","parMode":0,"pparMode":0,"timestamp":"2024-07-28T17:15:09.332575Z"},{"file":"batch1-41\\1001001\\pdata\\1\\","type":"Dataset","path":"","name":"batch1-41","procno":1,"expno":1001001,"title":"batch1-41\n87: [4-Formyl-2-methylthiazole, Zinc tetrafluoroborate, 4,4'-Oxydianiline]\nMULTISUPPDC_f\nPeaks for suppression at (in Hz):\n238.07; 186.34; 170.34; 101.83; ","date":"2024-02-29T18:18:18Z","dataType":null,"specType":"PROTON","sf":80.130494803,"pulProg":"zg30","nuclei":"1H","solvent":"CH3CN","parMode":0,"pparMode":0,"timestamp":"2024-07-28T17:15:20.694916Z"},{"file":"batch1-41\\1001002\\pdata\\1\\","type":"Dataset","path":"","name":"batch1-41","procno":1,"expno":1001002,"title":"batch1-41\n87: [4-Formyl-2-methylthiazole, Zinc tetrafluoroborate, 4,4'-Oxydianiline]\nMULTISUPPDC_f","date":"2024-02-29T18:18:29Z","dataType":null,"specType":"DEPT45","sf":20.150719396,"pulProg":"deptsp45","nuclei":"13C","solvent":"CH3CN","parMode":0,"pparMode":0,"timestamp":"2024-07-28T17:15:16.397362Z"},{"file":"batch1-42\\10\\pdata\\1\\","type":"Dataset","path":"","name":"batch1-42","procno":1,"expno":10,"title":"batch1-42\n88: [4-Formyl-2-methylthiazole, Iron(II) tetrafluoroborate hexahydrate, 4,4'-Methylenedianiline]\nMULTISUPPDC_f","date":"2024-02-29T18:37:14Z","dataType":null,"specType":"","sf":80.130376615,"pulProg":"noesycpdcgpps1d","nuclei":"1H","solvent":"CH3CN","parMode":0,"pparMode":0,"timestamp":"2024-07-28T17:15:22.134243Z"},{"file":"batch1-42\\1001001\\pdata\\1\\","type":"Dataset","path":"","name":"batch1-42","procno":1,"expno":1001001,"title":"batch1-42\n88: [4-Formyl-2-methylthiazole, Iron(II) tetrafluoroborate hexahydrate, 4,4'-Methylenedianiline]\nMULTISUPPDC_f\nPeaks for suppression at (in Hz):\n237.46; 169.71; 101.21; ","date":"2024-02-29T18:29:24Z","dataType":null,"specType":"PROTON","sf":80.130494803,"pulProg":"zg30","nuclei":"1H","solvent":"CH3CN","parMode":0,"pparMode":0,"timestamp":"2024-07-28T17:15:19.351263Z"},{"file":"batch1-42\\1001002\\pdata\\1\\","type":"Dataset","path":"","name":"batch1-42","procno":1,"expno":1001002,"title":"batch1-42\n88: [4-Formyl-2-methylthiazole, Iron(II) tetrafluoroborate hexahydrate, 4,4'-Methylenedianiline]\nMULTISUPPDC_f","date":"2024-02-29T18:29:36Z","dataType":null,"specType":"DEPT45","sf":20.150719396,"pulProg":"deptsp45","nuclei":"13C","solvent":"CH3CN","parMode":0,"pparMode":0,"timestamp":"2024-07-28T17:15:19.874854Z"},{"file":"batch1-43\\10\\pdata\\1\\","type":"Dataset","path":"","name":"batch1-43","procno":1,"expno":10,"title":"batch1-43\n89: [4-Formyl-2-methylthiazole, Iron(II) tetrafluoroborate hexahydrate, 2,2'-(Ethane-1,2-diylbis(oxy))diethanamine]\nMULTISUPPDC_f","date":"2024-02-29T18:48:23Z","dataType":null,"specType":"","sf":80.130376615,"pulProg":"noesycpdcgpps1d","nuclei":"1H","solvent":"CH3CN","parMode":0,"pparMode":0,"timestamp":"2024-07-28T17:15:21.497032Z"},{"file":"batch1-43\\1001001\\pdata\\1\\","type":"Dataset","path":"","name":"batch1-43","procno":1,"expno":1001001,"title":"batch1-43\n89: [4-Formyl-2-methylthiazole, Iron(II) tetrafluoroborate hexahydrate, 2,2'-(Ethane-1,2-diylbis(oxy))diethanamine]\nMULTISUPPDC_f\nPeaks for suppression at (in Hz):\n447.62; 236.89; 169.15; 100.66; ","date":"2024-02-29T18:40:36Z","dataType":null,"specType":"PROTON","sf":80.130494803,"pulProg":"zg30","nuclei":"1H","solvent":"CH3CN","parMode":0,"pparMode":0,"timestamp":"2024-07-28T17:15:17.914875Z"},{"file":"batch1-43\\1001002\\pdata\\1\\","type":"Dataset","path":"","name":"batch1-43","procno":1,"expno":1001002,"title":"batch1-43\n89: [4-Formyl-2-methylthiazole, Iron(II) tetrafluoroborate hexahydrate, 2,2'-(Ethane-1,2-diylbis(oxy))diethanamine]\nMULTISUPPDC_f\nPeaks for suppression at (in Hz):\n20.30; ","date":"2024-02-29T18:40:47Z","dataType":null,"specType":"DEPT45","sf":20.150719396,"pulProg":"deptsp45","nuclei":"13C","solvent":"CH3CN","parMode":0,"pparMode":0,"timestamp":"2024-07-28T17:15:09.340550Z"},{"file":"batch1-44\\10\\pdata\\1\\","type":"Dataset","path":"","name":"batch1-44","procno":1,"expno":10,"title":"batch1-44\n90: [4-Formyl-2-methylthiazole, Iron(II) tetrafluoroborate hexahydrate, 4,4'-Oxydianiline]\nMULTISUPPDC_f","date":"2024-02-29T18:59:29Z","dataType":null,"specType":"","sf":80.130376615,"pulProg":"noesycpdcgpps1d","nuclei":"1H","solvent":"CH3CN","parMode":0,"pparMode":0,"timestamp":"2024-07-28T17:15:20.700678Z"},{"file":"batch1-44\\1001001\\pdata\\1\\","type":"Dataset","path":"","name":"batch1-44","procno":1,"expno":1001001,"title":"batch1-44\n90: [4-Formyl-2-methylthiazole, Iron(II) tetrafluoroborate hexahydrate, 4,4'-Oxydianiline]\nMULTISUPPDC_f\nPeaks for suppression at (in Hz):\n236.01; 168.31; 99.76; ","date":"2024-02-29T18:51:42Z","dataType":null,"specType":"PROTON","sf":80.130494803,"pulProg":"zg30","nuclei":"1H","solvent":"CH3CN","parMode":0,"pparMode":0,"timestamp":"2024-07-28T17:15:16.412391Z"},{"file":"batch1-44\\1001002\\pdata\\1\\","type":"Dataset","path":"","name":"batch1-44","procno":1,"expno":1001002,"title":"batch1-44\n90: [4-Formyl-2-methylthiazole, Iron(II) tetrafluoroborate hexahydrate, 4,4'-Oxydianiline]\nMULTISUPPDC_f","date":"2024-02-29T18:51:53Z","dataType":null,"specType":"DEPT45","sf":20.150719396,"pulProg":"deptsp45","nuclei":"13C","solvent":"CH3CN","parMode":0,"pparMode":0,"timestamp":"2024-07-28T17:15:22.143888Z"},{"file":"batch1-45\\10\\pdata\\1\\","type":"Dataset","path":"","name":"batch1-45","procno":1,"expno":10,"title":"batch1-45\n91: [4-Formyl-2-methylthiazole, Naphthalene-1,8-diamine, Zinc tetrafluoroborate]\nMULTISUPPDC_f","date":"2024-02-29T19:10:36Z","dataType":null,"specType":"","sf":80.130376615,"pulProg":"noesycpdcgpps1d","nuclei":"1H","solvent":"CH3CN","parMode":0,"pparMode":0,"timestamp":"2024-07-28T17:15:19.358340Z"},{"file":"batch1-45\\1001001\\pdata\\1\\","type":"Dataset","path":"","name":"batch1-45","procno":1,"expno":1001001,"title":"batch1-45\n91: [4-Formyl-2-methylthiazole, Naphthalene-1,8-diamine, Zinc tetrafluoroborate]\nMULTISUPPDC_f\nPeaks for suppression at (in Hz):\n236.94; 169.18; 100.70; ","date":"2024-02-29T19:02:48Z","dataType":null,"specType":"PROTON","sf":80.130494803,"pulProg":"zg30","nuclei":"1H","solvent":"CH3CN","parMode":0,"pparMode":0,"timestamp":"2024-07-28T17:15:19.885462Z"},{"file":"batch1-45\\1001002\\pdata\\1\\","type":"Dataset","path":"","name":"batch1-45","procno":1,"expno":1001002,"title":"batch1-45\n91: [4-Formyl-2-methylthiazole, Naphthalene-1,8-diamine, Zinc tetrafluoroborate]\nMULTISUPPDC_f","date":"2024-02-29T19:03:00Z","dataType":null,"specType":"DEPT45","sf":20.150719396,"pulProg":"deptsp45","nuclei":"13C","solvent":"CH3CN","parMode":0,"pparMode":0,"timestamp":"2024-07-28T17:15:21.506397Z"},{"file":"batch1-46\\10\\pdata\\1\\","type":"Dataset","path":"","name":"batch1-46","procno":1,"expno":10,"title":"batch1-46\n92: [4-Formyl-2-methylthiazole, 4,4'-(9H-Fluorene-9,9-diyl)dianiline, Zinc tetrafluoroborate]\nMULTISUPPDC_f","date":"2024-02-29T19:21:44Z","dataType":null,"specType":"","sf":80.130376615,"pulProg":"noesycpdcgpps1d","nuclei":"1H","solvent":"CH3CN","parMode":0,"pparMode":0,"timestamp":"2024-07-28T17:15:19.146783Z"},{"file":"batch1-46\\1001001\\pdata\\1\\","type":"Dataset","path":"","name":"batch1-46","procno":1,"expno":1001001,"title":"batch1-46\n92: [4-Formyl-2-methylthiazole, 4,4'-(9H-Fluorene-9,9-diyl)dianiline, Zinc tetrafluoroborate]\nMULTISUPPDC_f\nPeaks for suppression at (in Hz):\n185.14; 169.72; ","date":"2024-02-29T19:13:55Z","dataType":null,"specType":"PROTON","sf":80.130494803,"pulProg":"zg30","nuclei":"1H","solvent":"CH3CN","parMode":0,"pparMode":0,"timestamp":"2024-07-28T17:15:09.368914Z"},{"file":"batch1-46\\1001002\\pdata\\1\\","type":"Dataset","path":"","name":"batch1-46","procno":1,"expno":1001002,"title":"batch1-46\n92: [4-Formyl-2-methylthiazole, 4,4'-(9H-Fluorene-9,9-diyl)dianiline, Zinc tetrafluoroborate]\nMULTISUPPDC_f","date":"2024-02-29T19:14:08Z","dataType":null,"specType":"DEPT45","sf":20.150719396,"pulProg":"deptsp45","nuclei":"13C","solvent":"CH3CN","parMode":0,"pparMode":0,"timestamp":"2024-07-28T17:15:20.707672Z"},{"file":"batch1-47\\10\\pdata\\1\\","type":"Dataset","path":"","name":"batch1-47","procno":1,"expno":10,"title":"batch1-47\n93: [4-Formyl-2-methylthiazole, Naphthalene-1,8-diamine, Iron(II) tetrafluoroborate hexahydrate]\nMULTISUPPDC_f","date":"2024-02-29T19:32:50Z","dataType":null,"specType":"","sf":80.130376615,"pulProg":"noesycpdcgpps1d","nuclei":"1H","solvent":"CH3CN","parMode":0,"pparMode":0,"timestamp":"2024-07-28T17:15:16.422080Z"},{"file":"batch1-47\\1001001\\pdata\\1\\","type":"Dataset","path":"","name":"batch1-47","procno":1,"expno":1001001,"title":"batch1-47\n93: [4-Formyl-2-methylthiazole, Naphthalene-1,8-diamine, Iron(II) tetrafluoroborate hexahydrate]\nMULTISUPPDC_f\nPeaks for suppression at (in Hz):\n173.29; ","date":"2024-02-29T19:25:04Z","dataType":null,"specType":"PROTON","sf":80.130494803,"pulProg":"zg30","nuclei":"1H","solvent":"CH3CN","parMode":0,"pparMode":0,"timestamp":"2024-07-28T17:15:22.156168Z"},{"file":"batch1-47\\1001002\\pdata\\1\\","type":"Dataset","path":"","name":"batch1-47","procno":1,"expno":1001002,"title":"batch1-47\n93: [4-Formyl-2-methylthiazole, Naphthalene-1,8-diamine, Iron(II) tetrafluoroborate hexahydrate]\nMULTISUPPDC_f\nPeaks for suppression at (in Hz):\n21.64; ","date":"2024-02-29T19:25:15Z","dataType":null,"specType":"DEPT45","sf":20.150719396,"pulProg":"deptsp45","nuclei":"13C","solvent":"CH3CN","parMode":0,"pparMode":0,"timestamp":"2024-07-28T17:15:19.366922Z"},{"file":"batch1-48\\10\\pdata\\1\\","type":"Dataset","path":"","name":"batch1-48","procno":1,"expno":10,"title":"batch1-48\n94: [4-Formyl-2-methylthiazole, 4,4'-(9H-Fluorene-9,9-diyl)dianiline, Iron(II) tetrafluoroborate hexahydrate]\nMULTISUPPDC_f","date":"2024-02-29T19:43:58Z","dataType":null,"specType":"","sf":80.130376615,"pulProg":"noesycpdcgpps1d","nuclei":"1H","solvent":"CH3CN","parMode":0,"pparMode":0,"timestamp":"2024-07-28T17:15:19.897201Z"},{"file":"batch1-48\\1001001\\pdata\\1\\","type":"Dataset","path":"","name":"batch1-48","procno":1,"expno":1001001,"title":"batch1-48\n94: [4-Formyl-2-methylthiazole, 4,4'-(9H-Fluorene-9,9-diyl)dianiline, Iron(II) tetrafluoroborate hexahydrate]\nMULTISUPPDC_f\nPeaks for suppression at (in Hz):\n170.52; ","date":"2024-02-29T19:36:10Z","dataType":null,"specType":"PROTON","sf":80.130494803,"pulProg":"zg30","nuclei":"1H","solvent":"CH3CN","parMode":0,"pparMode":0,"timestamp":"2024-07-28T17:15:21.514683Z"},{"file":"batch1-48\\1001002\\pdata\\1\\","type":"Dataset","path":"","name":"batch1-48","procno":1,"expno":1001002,"title":"batch1-48\n94: [4-Formyl-2-methylthiazole, 4,4'-(9H-Fluorene-9,9-diyl)dianiline, Iron(II) tetrafluoroborate hexahydrate]\nMULTISUPPDC_f","date":"2024-02-29T19:36:22Z","dataType":null,"specType":"DEPT45","sf":20.150719396,"pulProg":"deptsp45","nuclei":"13C","solvent":"CH3CN","parMode":0,"pparMode":0,"timestamp":"2024-07-28T17:15:19.149773Z"},{"file":"batch3-01\\10\\pdata\\1\\","type":"Dataset","path":"","name":"batch3-01","procno":1,"expno":10,"title":"batch3-01\n23batch3: [5-Methylpicolinaldehyde, Iron(II) tetrafluoroborate hexahydrate, 4,4'-Methylenedianiline] : [25, 1, 11]\nMULTISUPPDC_f","date":"2024-05-21T12:34:24Z","dataType":null,"specType":"","sf":80.130376615,"pulProg":"noesycpdcgpps1d","nuclei":"1H","solvent":"CH3CN","parMode":0,"pparMode":0,"timestamp":"2024-07-28T17:15:09.380268Z"},{"file":"batch3-01\\1001001\\pdata\\1\\","type":"Dataset","path":"","name":"batch3-01","procno":1,"expno":1001001,"title":"batch3-01\n23batch3: [5-Methylpicolinaldehyde, Iron(II) tetrafluoroborate hexahydrate, 4,4'-Methylenedianiline] : [25, 1, 11]\nMULTISUPPDC_f\nPeaks for suppression at (in Hz):\n218.02; 150.26; 81.78; ","date":"2024-05-21T12:32:34Z","dataType":null,"specType":"PROTON","sf":80.130494803,"pulProg":"zg30","nuclei":"1H","solvent":"CH3CN","parMode":0,"pparMode":0,"timestamp":"2024-07-28T17:15:20.711742Z"},{"file":"batch3-01\\1001002\\pdata\\1\\","type":"Dataset","path":"","name":"batch3-01","procno":1,"expno":1001002,"title":"batch3-01\n23batch3: [5-Methylpicolinaldehyde, Iron(II) tetrafluoroborate hexahydrate, 4,4'-Methylenedianiline] : [25, 1, 11]\nMULTISUPPDC_f","date":"2024-05-21T12:32:46Z","dataType":null,"specType":"DEPT45","sf":20.150719396,"pulProg":"deptsp45","nuclei":"13C","solvent":"CH3CN","parMode":0,"pparMode":0,"timestamp":"2024-07-28T17:15:16.429682Z"}]